swe2hs/__init__.py
swe2hs/_core.py
swe2hs/_default_model_parameters.py
swe2hs/one_dimensional.py
swe2hs/stepwise.py
swe2hs/two_dimensional.py
swe2hs/utils.py
swe2hs/visualization.py
swe2hs-1.0.4.dist-info/LICENSE.txt
swe2hs-1.0.4.dist-info/METADATA
swe2hs-1.0.4.dist-info/WHEEL
swe2hs-1.0.4.dist-info/top_level.txt
swe2hs-1.0.4.dist-info/RECORD
