Metadata-Version: 2.1
Name: swe2hs
Version: 1.0.4
Summary: Conceptual snow density model for transferring snow water equivalent to snow depth.
Home-page: https://code.wsl.ch/aschauer/swe2hs
Author: Johannes Aschauer
Author-email: johannes.aschauer@slf.ch
License: GPL-3.0-or-later
Project-URL: Documentation, https://aschauer.gitlab-pages.wsl.ch/swe2hs/
Project-URL: Changelog, https://aschauer.gitlab-pages.wsl.ch/swe2hs/changelog.html
Project-URL: Tracker, https://code.wsl.ch/aschauer/swe2hs/-/issues
Platform: any
Classifier: Development Status :: 4 - Beta
Classifier: Programming Language :: Python
Classifier: Programming Language :: Python :: 3.7
Classifier: Programming Language :: Python :: 3.8
Classifier: Programming Language :: Python :: 3.9
Classifier: Intended Audience :: Science/Research
Classifier: License :: OSI Approved :: GNU General Public License v3 (GPLv3)
Classifier: Topic :: Scientific/Engineering :: Hydrology
Classifier: Topic :: Scientific/Engineering :: Physics
License-File: LICENSE.txt
Requires-Dist: pandas (>=1.3)
Requires-Dist: netcdf4 (>=1.5.8)
Requires-Dist: numpy (>=1.18)
Requires-Dist: numba (>=0.55.1)
Requires-Dist: xarray[parallel] (>=0.19)
Requires-Dist: matplotlib (>=3.3)
Requires-Dist: importlib-metadata ; python_version < "3.8"
Provides-Extra: testing
Requires-Dist: setuptools ; extra == 'testing'
Requires-Dist: pytest ; extra == 'testing'
Requires-Dist: pytest-cov ; extra == 'testing'
